setup.py
calc_dist_ml/Binomialdistribution.py
calc_dist_ml/Gaussiandistribution.py
calc_dist_ml/Generaldistribution.py
calc_dist_ml/__init__.py
calc_dist_ml.egg-info/PKG-INFO
calc_dist_ml.egg-info/SOURCES.txt
calc_dist_ml.egg-info/dependency_links.txt
calc_dist_ml.egg-info/not-zip-safe
calc_dist_ml.egg-info/top_level.txt